{
  "$schema": "https://mintlify.com/docs.json",
  "theme": "mint",
  "name": "Finigami",
  "colors": {
    "primary": "#FFB231",
    "light": "#0a4e69",
    "dark": "#FFB231"
  },
  "favicon": "/favicon.ico",
  "navigation": {
    "groups": [
          {
            "group": "Index",
            "pages": [
              "introduction", 
              "credits",
              "authentication",
              "run-document-template"
            ]
          },
          {
            "group": "Endpoints",
            "openapi": {
              "source": "/api-reference/openapi.json",
              "directory": "api-reference"
            }
          }
      ],
    "global": {
      "anchors": []
    }
  },
  "logo": {
    "light": "/logo/light.svg",
    "dark": "/logo/dark.svg"
  },
  "navbar": {
    "links": [
      {
        "label": "Support",
        "href": "mailto:contact@finigami.com"
      }
    ],
    "primary": {
      "type": "button",
      "label": "Dashboard",
      "href": "https://www.finigami.com/sign-in"
    }
  },
  "footer": {
    "socials": {
      "linkedin": "https://www.linkedin.com/company/finigami"
    }
  },
  "api": {
    "mdx": {
      "server": "https://api.finigami.com/v1"
    },
    "playground": {
      "display": "none"
    }
  }
}